python_wekan-0.3.1.dist-info/licenses/LICENSE
tests/__init__.py
tests/test_cases.py
tests/test_enhancements.py
tests/test_unit.py
wekan/__init__.py
wekan/base.py
wekan/board.py
wekan/card.py
wekan/card_checklist.py
wekan/card_checklist_item.py
wekan/card_comment.py
wekan/customfield.py
wekan/integration.py
wekan/label.py
wekan/py.typed
wekan/swimlane.py
wekan/user.py
wekan/wekan_client.py
wekan/wekan_list.py
python_wekan-0.3.1.dist-info/METADATA
python_wekan-0.3.1.dist-info/WHEEL
python_wekan-0.3.1.dist-info/top_level.txt
python_wekan-0.3.1.dist-info/RECORD
