Metadata-Version: 2.4
Name: python-wekan
Version: 0.3.1
Summary: This is a python client for interacting with the WeKan® REST-API
Author: Bastian Wenske
License: BSD 3-Clause License
Project-URL: homepage, https://github.com/bastianwenske/python-wekan
Keywords: python
Classifier: Programming Language :: Python :: 3
Classifier: Typing :: Typed
Requires-Python: >=3.9
License-File: LICENSE
Requires-Dist: certifi==2024.7.4
Requires-Dist: charset-normalizer==3.3.2
Requires-Dist: idna==3.7
Requires-Dist: python-dateutil==2.9.0.post0
Requires-Dist: requests==2.32.4
Requires-Dist: six==1.16.0
Requires-Dist: urllib3==2.5.0
Dynamic: license-file
